dbt_cube_sync/__init__.py
dbt_cube_sync/cli.py
dbt_cube_sync/config.py
dbt_cube_sync/connectors/__init__.py
dbt_cube_sync/connectors/base.py
dbt_cube_sync/connectors/powerbi.py
dbt_cube_sync/connectors/superset.py
dbt_cube_sync/connectors/tableau.py
dbt_cube_sync/core/__init__.py
dbt_cube_sync/core/cube_generator.py
dbt_cube_sync/core/db_inspector.py
dbt_cube_sync/core/dbt_parser.py
dbt_cube_sync/core/models.py
dbt_cube_sync/core/state_manager.py
dbt_cube_sync-0.1.0a12.dist-info/METADATA
dbt_cube_sync-0.1.0a12.dist-info/WHEEL
dbt_cube_sync-0.1.0a12.dist-info/entry_points.txt
dbt_cube_sync-0.1.0a12.dist-info/RECORD
